[{"model":"base_de_dados.indicepluviometrico","pk":50400,"fields":{"ano":"2017","mes":"01","media_pluviometrica":98.6,"cidade":313}},{"model":"base_de_dados.indicepluviometrico","pk":50401,"fields":{"ano":"2017","mes":"02","media_pluviometrica":174.8,"cidade":313}},{"model":"base_de_dados.indicepluviometrico","pk":50402,"fields":{"ano":"2017","mes":"03","media_pluviometrica":286.2,"cidade":313}},{"model":"base_de_dados.indicepluviometrico","pk":50403,"fields":{"ano":"2017","mes":"04","media_pluviometrica":80.8,"cidade":313}},{"model":"base_de_dados.indicepluviometrico","pk":50404,"fields":{"ano":"2017","mes":"05","media_pluviometrica":68.4,"cidade":313}},{"model":"base_de_dados.indicepluviometrico","pk":50405,"fields":{"ano":"2017","mes":"06","media_pluviometrica":20.4,"cidade":313}},{"model":"base_de_dados.indicepluviometrico","pk":50406,"fields":{"ano":"2017","mes":"07","media_pluviometrica":29.4,"cidade":313}},{"model":"base_de_dados.indicepluviometrico","pk":50407,"fields":{"ano":"2017","mes":"08","media_pluviometrica":13.8,"cidade":313}},{"model":"base_de_dados.indicepluviometrico","pk":50408,"fields":{"ano":"2017","mes":"09","media_pluviometrica":0.0,"cidade":313}},{"model":"base_de_dados.indicepluviometrico","pk":50409,"fields":{"ano":"2017","mes":"10","media_pluviometrica":4.0,"cidade":313}},{"model":"base_de_dados.indicepluviometrico","pk":50410,"fields":{"ano":"2017","mes":"11","media_pluviometrica":0.0,"cidade":313}},{"model":"base_de_dados.indicepluviometrico","pk":50411,"fields":{"ano":"2017","mes":"12","media_pluviometrica":2.2,"cidade":313}},{"model":"base_de_dados.indicepluviometrico","pk":50412,"fields":{"ano":"2018","mes":"01","media_pluviometrica":51.0,"cidade":313}},{"model":"base_de_dados.indicepluviometrico","pk":50413,"fields":{"ano":"2018","mes":"02","media_pluviometrica":407.2,"cidade":313}},{"model":"base_de_dados.indicepluviometrico","pk":50414,"fields":{"ano":"2018","mes":"03","media_pluviometrica":63.4,"cidade":313}},{"model":"base_de_dados.indicepluviometrico","pk":50415,"fields":{"ano":"2018","mes":"04","media_pluviometrica":0.0,"cidade":313}},{"model":"base_de_dados.indicepluviometrico","pk":50416,"fields":{"ano":"2018","mes":"05","media_pluviometrica":0.0,"cidade":313}},{"model":"base_de_dados.indicepluviometrico","pk":50417,"fields":{"ano":"2018","mes":"06","media_pluviometrica":0.0,"cidade":313}},{"model":"base_de_dados.indicepluviometrico","pk":50418,"fields":{"ano":"2018","mes":"07","media_pluviometrica":2.0,"cidade":313}},{"model":"base_de_dados.indicepluviometrico","pk":50419,"fields":{"ano":"2018","mes":"08","media_pluviometrica":1.0,"cidade":313}},{"model":"base_de_dados.indicepluviometrico","pk":50420,"fields":{"ano":"2018","mes":"09","media_pluviometrica":0.0,"cidade":313}},{"model":"base_de_dados.indicepluviometrico","pk":50421,"fields":{"ano":"2018","mes":"10","media_pluviometrica":0.0,"cidade":313}},{"model":"base_de_dados.indicepluviometrico","pk":50422,"fields":{"ano":"2018","mes":"11","media_pluviometrica":0.0,"cidade":313}},{"model":"base_de_dados.indicepluviometrico","pk":50423,"fields":{"ano":"2018","mes":"12","media_pluviometrica":173.2,"cidade":313}},{"model":"base_de_dados.indicepluviometrico","pk":50424,"fields":{"ano":"2019","mes":"01","media_pluviometrica":143.0,"cidade":313}},{"model":"base_de_dados.indicepluviometrico","pk":50425,"fields":{"ano":"2019","mes":"02","media_pluviometrica":148.4,"cidade":313}},{"model":"base_de_dados.indicepluviometrico","pk":50426,"fields":{"ano":"2019","mes":"03","media_pluviometrica":254.4,"cidade":313}},{"model":"base_de_dados.indicepluviometrico","pk":50427,"fields":{"ano":"2019","mes":"04","media_pluviometrica":281.0,"cidade":313}},{"model":"base_de_dados.indicepluviometrico","pk":50428,"fields":{"ano":"2019","mes":"05","media_pluviometrica":46.2,"cidade":313}},{"model":"base_de_dados.indicepluviometrico","pk":50429,"fields":{"ano":"2019","mes":"06","media_pluviometrica":0.2,"cidade":313}},{"model":"base_de_dados.indicepluviometrico","pk":50430,"fields":{"ano":"2019","mes":"07","media_pluviometrica":86.6,"cidade":313}},{"model":"base_de_dados.indicepluviometrico","pk":50431,"fields":{"ano":"2019","mes":"08","media_pluviometrica":6.6,"cidade":313}},{"model":"base_de_dados.indicepluviometrico","pk":50432,"fields":{"ano":"2019","mes":"09","media_pluviometrica":20.8,"cidade":313}},{"model":"base_de_dados.indicepluviometrico","pk":50433,"fields":{"ano":"2019","mes":"10","media_pluviometrica":0.0,"cidade":313}},{"model":"base_de_dados.indicepluviometrico","pk":50434,"fields":{"ano":"2019","mes":"11","media_pluviometrica":0.2,"cidade":313}},{"model":"base_de_dados.indicepluviometrico","pk":50435,"fields":{"ano":"2019","mes":"12","media_pluviometrica":12.4,"cidade":313}},{"model":"base_de_dados.indicepluviometrico","pk":50436,"fields":{"ano":"2020","mes":"01","media_pluviometrica":228.2,"cidade":313}},{"model":"base_de_dados.indicepluviometrico","pk":50437,"fields":{"ano":"2020","mes":"02","media_pluviometrica":176.0,"cidade":313}},{"model":"base_de_dados.indicepluviometrico","pk":50438,"fields":{"ano":"2020","mes":"03","media_pluviometrica":418.6,"cidade":313}},{"model":"base_de_dados.indicepluviometrico","pk":50439,"fields":{"ano":"2020","mes":"04","media_pluviometrica":347.4,"cidade":313}},{"model":"base_de_dados.indicepluviometrico","pk":50440,"fields":{"ano":"2020","mes":"05","media_pluviometrica":94.0,"cidade":313}},{"model":"base_de_dados.indicepluviometrico","pk":50441,"fields":{"ano":"2020","mes":"06","media_pluviometrica":119.2,"cidade":313}},{"model":"base_de_dados.indicepluviometrico","pk":50442,"fields":{"ano":"2020","mes":"07","media_pluviometrica":21.8,"cidade":313}},{"model":"base_de_dados.indicepluviometrico","pk":50443,"fields":{"ano":"2020","mes":"08","media_pluviometrica":2.2,"cidade":313}},{"model":"base_de_dados.indicepluviometrico","pk":50444,"fields":{"ano":"2020","mes":"09","media_pluviometrica":0.0,"cidade":313}},{"model":"base_de_dados.indicepluviometrico","pk":50445,"fields":{"ano":"2020","mes":"10","media_pluviometrica":0.0,"cidade":313}},{"model":"base_de_dados.indicepluviometrico","pk":50446,"fields":{"ano":"2020","mes":"11","media_pluviometrica":97.2,"cidade":313}},{"model":"base_de_dados.indicepluviometrico","pk":50447,"fields":{"ano":"2020","mes":"12","media_pluviometrica":0.0,"cidade":313}},{"model":"base_de_dados.indicepluviometrico","pk":50448,"fields":{"ano":"2021","mes":"01","media_pluviometrica":91.6,"cidade":313}},{"model":"base_de_dados.indicepluviometrico","pk":50449,"fields":{"ano":"2021","mes":"02","media_pluviometrica":148.2,"cidade":313}},{"model":"base_de_dados.indicepluviometrico","pk":50450,"fields":{"ano":"2021","mes":"03","media_pluviometrica":267.4,"cidade":313}},{"model":"base_de_dados.indicepluviometrico","pk":50451,"fields":{"ano":"2021","mes":"04","media_pluviometrica":149.8,"cidade":313}},{"model":"base_de_dados.indicepluviometrico","pk":50452,"fields":{"ano":"2021","mes":"05","media_pluviometrica":215.8,"cidade":313}},{"model":"base_de_dados.indicepluviometrico","pk":50453,"fields":{"ano":"2021","mes":"06","media_pluviometrica":16.8,"cidade":313}},{"model":"base_de_dados.indicepluviometrico","pk":50454,"fields":{"ano":"2021","mes":"07","media_pluviometrica":0.0,"cidade":313}},{"model":"base_de_dados.indicepluviometrico","pk":50455,"fields":{"ano":"2021","mes":"08","media_pluviometrica":13.6,"cidade":313}},{"model":"base_de_dados.indicepluviometrico","pk":50456,"fields":{"ano":"2021","mes":"09","media_pluviometrica":1.2,"cidade":313}},{"model":"base_de_dados.indicepluviometrico","pk":50457,"fields":{"ano":"2021","mes":"10","media_pluviometrica":0.0,"cidade":313}},{"model":"base_de_dados.indicepluviometrico","pk":50458,"fields":{"ano":"2021","mes":"11","media_pluviometrica":0.0,"cidade":313}},{"model":"base_de_dados.indicepluviometrico","pk":50459,"fields":{"ano":"2021","mes":"12","media_pluviometrica":13.2,"cidade":313}},{"model":"base_de_dados.indicepluviometrico","pk":50460,"fields":{"ano":"2003","mes":"01","media_pluviometrica":0.0,"cidade":313}},{"model":"base_de_dados.indicepluviometrico","pk":50461,"fields":{"ano":"2003","mes":"02","media_pluviometrica":276.4,"cidade":313}},{"model":"base_de_dados.indicepluviometrico","pk":50462,"fields":{"ano":"2003","mes":"03","media_pluviometrica":237.0,"cidade":313}},{"model":"base_de_dados.indicepluviometrico","pk":50463,"fields":{"ano":"2003","mes":"04","media_pluviometrica":233.2,"cidade":313}},{"model":"base_de_dados.indicepluviometrico","pk":50464,"fields":{"ano":"2003","mes":"05","media_pluviometrica":48.8,"cidade":313}},{"model":"base_de_dados.indicepluviometrico","pk":50465,"fields":{"ano":"2003","mes":"06","media_pluviometrica":15.0,"cidade":313}},{"model":"base_de_dados.indicepluviometrico","pk":50466,"fields":{"ano":"2003","mes":"07","media_pluviometrica":1.6,"cidade":313}},{"model":"base_de_dados.indicepluviometrico","pk":50467,"fields":{"ano":"2003","mes":"08","media_pluviometrica":0.0,"cidade":313}},{"model":"base_de_dados.indicepluviometrico","pk":50468,"fields":{"ano":"2003","mes":"09","media_pluviometrica":1.0,"cidade":313}},{"model":"base_de_dados.indicepluviometrico","pk":50469,"fields":{"ano":"2003","mes":"10","media_pluviometrica":0.0,"cidade":313}},{"model":"base_de_dados.indicepluviometrico","pk":50470,"fields":{"ano":"2003","mes":"11","media_pluviometrica":0.0,"cidade":313}},{"model":"base_de_dados.indicepluviometrico","pk":50471,"fields":{"ano":"2003","mes":"12","media_pluviometrica":30.0,"cidade":313}},{"model":"base_de_dados.indicepluviometrico","pk":50472,"fields":{"ano":"2005","mes":"01","media_pluviometrica":100.2,"cidade":314}},{"model":"base_de_dados.indicepluviometrico","pk":50473,"fields":{"ano":"2005","mes":"02","media_pluviometrica":145.6,"cidade":314}},{"model":"base_de_dados.indicepluviometrico","pk":50474,"fields":{"ano":"2005","mes":"03","media_pluviometrica":81.0,"cidade":314}},{"model":"base_de_dados.indicepluviometrico","pk":50475,"fields":{"ano":"2005","mes":"04","media_pluviometrica":156.8,"cidade":314}},{"model":"base_de_dados.indicepluviometrico","pk":50476,"fields":{"ano":"2005","mes":"05","media_pluviometrica":0.4,"cidade":314}},{"model":"base_de_dados.indicepluviometrico","pk":50477,"fields":{"ano":"2005","mes":"06","media_pluviometrica":0.0,"cidade":314}},{"model":"base_de_dados.indicepluviometrico","pk":50478,"fields":{"ano":"2005","mes":"07","media_pluviometrica":0.0,"cidade":314}},{"model":"base_de_dados.indicepluviometrico","pk":50479,"fields":{"ano":"2005","mes":"08","media_pluviometrica":0.0,"cidade":314}},{"model":"base_de_dados.indicepluviometrico","pk":50480,"fields":{"ano":"2005","mes":"09","media_pluviometrica":0.0,"cidade":314}},{"model":"base_de_dados.indicepluviometrico","pk":50481,"fields":{"ano":"2005","mes":"10","media_pluviometrica":6.2,"cidade":314}},{"model":"base_de_dados.indicepluviometrico","pk":50482,"fields":{"ano":"2005","mes":"11","media_pluviometrica":28.4,"cidade":314}},{"model":"base_de_dados.indicepluviometrico","pk":50483,"fields":{"ano":"2005","mes":"12","media_pluviometrica":118.6,"cidade":314}},{"model":"base_de_dados.indicepluviometrico","pk":50484,"fields":{"ano":"2006","mes":"01","media_pluviometrica":63.2,"cidade":314}},{"model":"base_de_dados.indicepluviometrico","pk":50485,"fields":{"ano":"2006","mes":"02","media_pluviometrica":177.6,"cidade":314}},{"model":"base_de_dados.indicepluviometrico","pk":50486,"fields":{"ano":"2006","mes":"03","media_pluviometrica":356.6,"cidade":314}},{"model":"base_de_dados.indicepluviometrico","pk":50487,"fields":{"ano":"2006","mes":"04","media_pluviometrica":300.8,"cidade":314}},{"model":"base_de_dados.indicepluviometrico","pk":50488,"fields":{"ano":"2006","mes":"05","media_pluviometrica":27.0,"cidade":314}},{"model":"base_de_dados.indicepluviometrico","pk":50489,"fields":{"ano":"2006","mes":"06","media_pluviometrica":0.6,"cidade":314}},{"model":"base_de_dados.indicepluviometrico","pk":50490,"fields":{"ano":"2006","mes":"07","media_pluviometrica":0.4,"cidade":314}},{"model":"base_de_dados.indicepluviometrico","pk":50491,"fields":{"ano":"2006","mes":"08","media_pluviometrica":0.0,"cidade":314}},{"model":"base_de_dados.indicepluviometrico","pk":50492,"fields":{"ano":"2006","mes":"09","media_pluviometrica":34.8,"cidade":314}},{"model":"base_de_dados.indicepluviometrico","pk":50493,"fields":{"ano":"2006","mes":"10","media_pluviometrica":141.2,"cidade":314}},{"model":"base_de_dados.indicepluviometrico","pk":50494,"fields":{"ano":"2006","mes":"11","media_pluviometrica":56.2,"cidade":314}},{"model":"base_de_dados.indicepluviometrico","pk":50495,"fields":{"ano":"2006","mes":"12","media_pluviometrica":26.8,"cidade":314}},{"model":"base_de_dados.indicepluviometrico","pk":50496,"fields":{"ano":"2007","mes":"01","media_pluviometrica":0.6,"cidade":314}},{"model":"base_de_dados.indicepluviometrico","pk":50497,"fields":{"ano":"2007","mes":"02","media_pluviometrica":2.0,"cidade":314}},{"model":"base_de_dados.indicepluviometrico","pk":50498,"fields":{"ano":"2007","mes":"03","media_pluviometrica":0.4,"cidade":314}},{"model":"base_de_dados.indicepluviometrico","pk":50499,"fields":{"ano":"2007","mes":"04","media_pluviometrica":0.8,"cidade":314}}]