[{"model":"base_de_dados.indicepluviometrico","pk":27300,"fields":{"ano":"2016","mes":"01","media_pluviometrica":330.8,"cidade":165}},{"model":"base_de_dados.indicepluviometrico","pk":27301,"fields":{"ano":"2016","mes":"02","media_pluviometrica":38.0,"cidade":165}},{"model":"base_de_dados.indicepluviometrico","pk":27302,"fields":{"ano":"2016","mes":"03","media_pluviometrica":0.0,"cidade":165}},{"model":"base_de_dados.indicepluviometrico","pk":27303,"fields":{"ano":"2016","mes":"04","media_pluviometrica":3.4,"cidade":165}},{"model":"base_de_dados.indicepluviometrico","pk":27304,"fields":{"ano":"2016","mes":"05","media_pluviometrica":9.6,"cidade":165}},{"model":"base_de_dados.indicepluviometrico","pk":27305,"fields":{"ano":"2016","mes":"06","media_pluviometrica":8.6,"cidade":165}},{"model":"base_de_dados.indicepluviometrico","pk":27306,"fields":{"ano":"2016","mes":"07","media_pluviometrica":0.6,"cidade":165}},{"model":"base_de_dados.indicepluviometrico","pk":27307,"fields":{"ano":"2016","mes":"08","media_pluviometrica":57.4,"cidade":165}},{"model":"base_de_dados.indicepluviometrico","pk":27308,"fields":{"ano":"2016","mes":"09","media_pluviometrica":59.8,"cidade":165}},{"model":"base_de_dados.indicepluviometrico","pk":27309,"fields":{"ano":"2016","mes":"10","media_pluviometrica":67.2,"cidade":165}},{"model":"base_de_dados.indicepluviometrico","pk":27310,"fields":{"ano":"2016","mes":"11","media_pluviometrica":0.0,"cidade":165}},{"model":"base_de_dados.indicepluviometrico","pk":27311,"fields":{"ano":"2016","mes":"12","media_pluviometrica":0.0,"cidade":165}},{"model":"base_de_dados.indicepluviometrico","pk":27312,"fields":{"ano":"2017","mes":"01","media_pluviometrica":0.0,"cidade":165}},{"model":"base_de_dados.indicepluviometrico","pk":27313,"fields":{"ano":"2017","mes":"02","media_pluviometrica":0.0,"cidade":165}},{"model":"base_de_dados.indicepluviometrico","pk":27314,"fields":{"ano":"2017","mes":"03","media_pluviometrica":0.0,"cidade":165}},{"model":"base_de_dados.indicepluviometrico","pk":27315,"fields":{"ano":"2017","mes":"04","media_pluviometrica":0.0,"cidade":165}},{"model":"base_de_dados.indicepluviometrico","pk":27316,"fields":{"ano":"2017","mes":"05","media_pluviometrica":44.8,"cidade":165}},{"model":"base_de_dados.indicepluviometrico","pk":27317,"fields":{"ano":"2017","mes":"06","media_pluviometrica":71.0,"cidade":165}},{"model":"base_de_dados.indicepluviometrico","pk":27318,"fields":{"ano":"2017","mes":"07","media_pluviometrica":0.2,"cidade":165}},{"model":"base_de_dados.indicepluviometrico","pk":27319,"fields":{"ano":"2017","mes":"08","media_pluviometrica":35.6,"cidade":165}},{"model":"base_de_dados.indicepluviometrico","pk":27320,"fields":{"ano":"2017","mes":"09","media_pluviometrica":3.6,"cidade":165}},{"model":"base_de_dados.indicepluviometrico","pk":27321,"fields":{"ano":"2017","mes":"10","media_pluviometrica":61.0,"cidade":165}},{"model":"base_de_dados.indicepluviometrico","pk":27322,"fields":{"ano":"2017","mes":"11","media_pluviometrica":30.2,"cidade":165}},{"model":"base_de_dados.indicepluviometrico","pk":27323,"fields":{"ano":"2017","mes":"12","media_pluviometrica":0.0,"cidade":165}},{"model":"base_de_dados.indicepluviometrico","pk":27324,"fields":{"ano":"2018","mes":"01","media_pluviometrica":30.8,"cidade":165}},{"model":"base_de_dados.indicepluviometrico","pk":27325,"fields":{"ano":"2018","mes":"02","media_pluviometrica":0.0,"cidade":165}},{"model":"base_de_dados.indicepluviometrico","pk":27326,"fields":{"ano":"2018","mes":"03","media_pluviometrica":0.0,"cidade":165}},{"model":"base_de_dados.indicepluviometrico","pk":27327,"fields":{"ano":"2018","mes":"04","media_pluviometrica":0.0,"cidade":165}},{"model":"base_de_dados.indicepluviometrico","pk":27328,"fields":{"ano":"2018","mes":"05","media_pluviometrica":0.0,"cidade":165}},{"model":"base_de_dados.indicepluviometrico","pk":27329,"fields":{"ano":"2018","mes":"06","media_pluviometrica":9.8,"cidade":165}},{"model":"base_de_dados.indicepluviometrico","pk":27330,"fields":{"ano":"2018","mes":"07","media_pluviometrica":2.0,"cidade":165}},{"model":"base_de_dados.indicepluviometrico","pk":27331,"fields":{"ano":"2018","mes":"08","media_pluviometrica":1.2,"cidade":165}},{"model":"base_de_dados.indicepluviometrico","pk":27332,"fields":{"ano":"2018","mes":"09","media_pluviometrica":49.4,"cidade":165}},{"model":"base_de_dados.indicepluviometrico","pk":27333,"fields":{"ano":"2018","mes":"10","media_pluviometrica":46.4,"cidade":165}},{"model":"base_de_dados.indicepluviometrico","pk":27334,"fields":{"ano":"2018","mes":"11","media_pluviometrica":105.2,"cidade":165}},{"model":"base_de_dados.indicepluviometrico","pk":27335,"fields":{"ano":"2018","mes":"12","media_pluviometrica":52.8,"cidade":165}},{"model":"base_de_dados.indicepluviometrico","pk":27336,"fields":{"ano":"2019","mes":"01","media_pluviometrica":6.8,"cidade":165}},{"model":"base_de_dados.indicepluviometrico","pk":27337,"fields":{"ano":"2019","mes":"02","media_pluviometrica":146.0,"cidade":165}},{"model":"base_de_dados.indicepluviometrico","pk":27338,"fields":{"ano":"2019","mes":"03","media_pluviometrica":57.8,"cidade":165}},{"model":"base_de_dados.indicepluviometrico","pk":27339,"fields":{"ano":"2019","mes":"04","media_pluviometrica":149.2,"cidade":165}},{"model":"base_de_dados.indicepluviometrico","pk":27340,"fields":{"ano":"2019","mes":"05","media_pluviometrica":31.2,"cidade":165}},{"model":"base_de_dados.indicepluviometrico","pk":27341,"fields":{"ano":"2019","mes":"06","media_pluviometrica":28.0,"cidade":165}},{"model":"base_de_dados.indicepluviometrico","pk":27342,"fields":{"ano":"2019","mes":"07","media_pluviometrica":7.4,"cidade":165}},{"model":"base_de_dados.indicepluviometrico","pk":27343,"fields":{"ano":"2019","mes":"08","media_pluviometrica":17.0,"cidade":165}},{"model":"base_de_dados.indicepluviometrico","pk":27344,"fields":{"ano":"2019","mes":"09","media_pluviometrica":19.8,"cidade":165}},{"model":"base_de_dados.indicepluviometrico","pk":27345,"fields":{"ano":"2019","mes":"10","media_pluviometrica":11.4,"cidade":165}},{"model":"base_de_dados.indicepluviometrico","pk":27346,"fields":{"ano":"2019","mes":"11","media_pluviometrica":52.0,"cidade":165}},{"model":"base_de_dados.indicepluviometrico","pk":27347,"fields":{"ano":"2019","mes":"12","media_pluviometrica":72.4,"cidade":165}},{"model":"base_de_dados.indicepluviometrico","pk":27348,"fields":{"ano":"2020","mes":"01","media_pluviometrica":101.8,"cidade":165}},{"model":"base_de_dados.indicepluviometrico","pk":27349,"fields":{"ano":"2020","mes":"02","media_pluviometrica":123.0,"cidade":165}},{"model":"base_de_dados.indicepluviometrico","pk":27350,"fields":{"ano":"2020","mes":"03","media_pluviometrica":49.6,"cidade":165}},{"model":"base_de_dados.indicepluviometrico","pk":27351,"fields":{"ano":"2020","mes":"04","media_pluviometrica":76.2,"cidade":165}},{"model":"base_de_dados.indicepluviometrico","pk":27352,"fields":{"ano":"2020","mes":"05","media_pluviometrica":59.2,"cidade":165}},{"model":"base_de_dados.indicepluviometrico","pk":27353,"fields":{"ano":"2020","mes":"06","media_pluviometrica":19.2,"cidade":165}},{"model":"base_de_dados.indicepluviometrico","pk":27354,"fields":{"ano":"2020","mes":"07","media_pluviometrica":0.2,"cidade":165}},{"model":"base_de_dados.indicepluviometrico","pk":27355,"fields":{"ano":"2020","mes":"08","media_pluviometrica":22.2,"cidade":165}},{"model":"base_de_dados.indicepluviometrico","pk":27356,"fields":{"ano":"2020","mes":"09","media_pluviometrica":6.4,"cidade":165}},{"model":"base_de_dados.indicepluviometrico","pk":27357,"fields":{"ano":"2020","mes":"10","media_pluviometrica":120.8,"cidade":165}},{"model":"base_de_dados.indicepluviometrico","pk":27358,"fields":{"ano":"2020","mes":"11","media_pluviometrica":11.4,"cidade":165}},{"model":"base_de_dados.indicepluviometrico","pk":27359,"fields":{"ano":"2020","mes":"12","media_pluviometrica":153.2,"cidade":165}},{"model":"base_de_dados.indicepluviometrico","pk":27360,"fields":{"ano":"2021","mes":"01","media_pluviometrica":344.0,"cidade":165}},{"model":"base_de_dados.indicepluviometrico","pk":27361,"fields":{"ano":"2021","mes":"02","media_pluviometrica":42.0,"cidade":165}},{"model":"base_de_dados.indicepluviometrico","pk":27362,"fields":{"ano":"2021","mes":"03","media_pluviometrica":70.0,"cidade":165}},{"model":"base_de_dados.indicepluviometrico","pk":27363,"fields":{"ano":"2021","mes":"04","media_pluviometrica":36.4,"cidade":165}},{"model":"base_de_dados.indicepluviometrico","pk":27364,"fields":{"ano":"2021","mes":"05","media_pluviometrica":10.6,"cidade":165}},{"model":"base_de_dados.indicepluviometrico","pk":27365,"fields":{"ano":"2021","mes":"06","media_pluviometrica":11.6,"cidade":165}},{"model":"base_de_dados.indicepluviometrico","pk":27366,"fields":{"ano":"2021","mes":"07","media_pluviometrica":5.6,"cidade":165}},{"model":"base_de_dados.indicepluviometrico","pk":27367,"fields":{"ano":"2021","mes":"08","media_pluviometrica":5.0,"cidade":165}},{"model":"base_de_dados.indicepluviometrico","pk":27368,"fields":{"ano":"2021","mes":"09","media_pluviometrica":5.8,"cidade":165}},{"model":"base_de_dados.indicepluviometrico","pk":27369,"fields":{"ano":"2021","mes":"10","media_pluviometrica":25.0,"cidade":165}},{"model":"base_de_dados.indicepluviometrico","pk":27370,"fields":{"ano":"2021","mes":"11","media_pluviometrica":0.4,"cidade":165}},{"model":"base_de_dados.indicepluviometrico","pk":27371,"fields":{"ano":"2021","mes":"12","media_pluviometrica":0.0,"cidade":165}},{"model":"base_de_dados.indicepluviometrico","pk":27372,"fields":{"ano":"2006","mes":"01","media_pluviometrica":0.0,"cidade":165}},{"model":"base_de_dados.indicepluviometrico","pk":27373,"fields":{"ano":"2006","mes":"02","media_pluviometrica":0.0,"cidade":165}},{"model":"base_de_dados.indicepluviometrico","pk":27374,"fields":{"ano":"2006","mes":"03","media_pluviometrica":0.0,"cidade":165}},{"model":"base_de_dados.indicepluviometrico","pk":27375,"fields":{"ano":"2006","mes":"04","media_pluviometrica":0.0,"cidade":165}},{"model":"base_de_dados.indicepluviometrico","pk":27376,"fields":{"ano":"2006","mes":"05","media_pluviometrica":0.0,"cidade":165}},{"model":"base_de_dados.indicepluviometrico","pk":27377,"fields":{"ano":"2006","mes":"06","media_pluviometrica":0.0,"cidade":165}},{"model":"base_de_dados.indicepluviometrico","pk":27378,"fields":{"ano":"2006","mes":"07","media_pluviometrica":0.0,"cidade":165}},{"model":"base_de_dados.indicepluviometrico","pk":27379,"fields":{"ano":"2006","mes":"08","media_pluviometrica":0.0,"cidade":165}},{"model":"base_de_dados.indicepluviometrico","pk":27380,"fields":{"ano":"2006","mes":"09","media_pluviometrica":0.0,"cidade":165}},{"model":"base_de_dados.indicepluviometrico","pk":27381,"fields":{"ano":"2006","mes":"10","media_pluviometrica":0.6,"cidade":165}},{"model":"base_de_dados.indicepluviometrico","pk":27382,"fields":{"ano":"2006","mes":"11","media_pluviometrica":252.2,"cidade":165}},{"model":"base_de_dados.indicepluviometrico","pk":27383,"fields":{"ano":"2006","mes":"12","media_pluviometrica":243.6,"cidade":165}},{"model":"base_de_dados.indicepluviometrico","pk":27384,"fields":{"ano":"2007","mes":"01","media_pluviometrica":248.4,"cidade":166}},{"model":"base_de_dados.indicepluviometrico","pk":27385,"fields":{"ano":"2007","mes":"02","media_pluviometrica":65.0,"cidade":166}},{"model":"base_de_dados.indicepluviometrico","pk":27386,"fields":{"ano":"2007","mes":"03","media_pluviometrica":24.6,"cidade":166}},{"model":"base_de_dados.indicepluviometrico","pk":27387,"fields":{"ano":"2007","mes":"04","media_pluviometrica":31.0,"cidade":166}},{"model":"base_de_dados.indicepluviometrico","pk":27388,"fields":{"ano":"2007","mes":"05","media_pluviometrica":2.4,"cidade":166}},{"model":"base_de_dados.indicepluviometrico","pk":27389,"fields":{"ano":"2007","mes":"06","media_pluviometrica":0.0,"cidade":166}},{"model":"base_de_dados.indicepluviometrico","pk":27390,"fields":{"ano":"2007","mes":"07","media_pluviometrica":5.4,"cidade":166}},{"model":"base_de_dados.indicepluviometrico","pk":27391,"fields":{"ano":"2007","mes":"08","media_pluviometrica":0.0,"cidade":166}},{"model":"base_de_dados.indicepluviometrico","pk":27392,"fields":{"ano":"2007","mes":"09","media_pluviometrica":0.0,"cidade":166}},{"model":"base_de_dados.indicepluviometrico","pk":27393,"fields":{"ano":"2007","mes":"10","media_pluviometrica":26.8,"cidade":166}},{"model":"base_de_dados.indicepluviometrico","pk":27394,"fields":{"ano":"2007","mes":"11","media_pluviometrica":48.4,"cidade":166}},{"model":"base_de_dados.indicepluviometrico","pk":27395,"fields":{"ano":"2007","mes":"12","media_pluviometrica":46.4,"cidade":166}},{"model":"base_de_dados.indicepluviometrico","pk":27396,"fields":{"ano":"2008","mes":"01","media_pluviometrica":57.2,"cidade":166}},{"model":"base_de_dados.indicepluviometrico","pk":27397,"fields":{"ano":"2008","mes":"02","media_pluviometrica":89.2,"cidade":166}},{"model":"base_de_dados.indicepluviometrico","pk":27398,"fields":{"ano":"2008","mes":"03","media_pluviometrica":87.0,"cidade":166}},{"model":"base_de_dados.indicepluviometrico","pk":27399,"fields":{"ano":"2008","mes":"04","media_pluviometrica":94.8,"cidade":166}}]