[{"model":"base_de_dados.indicepluviometrico","pk":38900,"fields":{"ano":"2011","mes":"09","media_pluviometrica":72.6,"cidade":240}},{"model":"base_de_dados.indicepluviometrico","pk":38901,"fields":{"ano":"2011","mes":"10","media_pluviometrica":144.4,"cidade":240}},{"model":"base_de_dados.indicepluviometrico","pk":38902,"fields":{"ano":"2011","mes":"11","media_pluviometrica":137.2,"cidade":240}},{"model":"base_de_dados.indicepluviometrico","pk":38903,"fields":{"ano":"2011","mes":"12","media_pluviometrica":258.0,"cidade":240}},{"model":"base_de_dados.indicepluviometrico","pk":38904,"fields":{"ano":"2012","mes":"01","media_pluviometrica":409.6,"cidade":240}},{"model":"base_de_dados.indicepluviometrico","pk":38905,"fields":{"ano":"2012","mes":"02","media_pluviometrica":319.6,"cidade":240}},{"model":"base_de_dados.indicepluviometrico","pk":38906,"fields":{"ano":"2012","mes":"03","media_pluviometrica":551.8,"cidade":240}},{"model":"base_de_dados.indicepluviometrico","pk":38907,"fields":{"ano":"2012","mes":"04","media_pluviometrica":306.0,"cidade":240}},{"model":"base_de_dados.indicepluviometrico","pk":38908,"fields":{"ano":"2012","mes":"05","media_pluviometrica":213.2,"cidade":240}},{"model":"base_de_dados.indicepluviometrico","pk":38909,"fields":{"ano":"2012","mes":"06","media_pluviometrica":318.2,"cidade":240}},{"model":"base_de_dados.indicepluviometrico","pk":38910,"fields":{"ano":"2012","mes":"07","media_pluviometrica":241.4,"cidade":240}},{"model":"base_de_dados.indicepluviometrico","pk":38911,"fields":{"ano":"2012","mes":"08","media_pluviometrica":122.0,"cidade":240}},{"model":"base_de_dados.indicepluviometrico","pk":38912,"fields":{"ano":"2012","mes":"09","media_pluviometrica":189.6,"cidade":240}},{"model":"base_de_dados.indicepluviometrico","pk":38913,"fields":{"ano":"2012","mes":"10","media_pluviometrica":45.4,"cidade":240}},{"model":"base_de_dados.indicepluviometrico","pk":38914,"fields":{"ano":"2012","mes":"11","media_pluviometrica":58.8,"cidade":240}},{"model":"base_de_dados.indicepluviometrico","pk":38915,"fields":{"ano":"2012","mes":"12","media_pluviometrica":294.0,"cidade":240}},{"model":"base_de_dados.indicepluviometrico","pk":38916,"fields":{"ano":"2013","mes":"01","media_pluviometrica":363.8,"cidade":240}},{"model":"base_de_dados.indicepluviometrico","pk":38917,"fields":{"ano":"2013","mes":"02","media_pluviometrica":394.4,"cidade":240}},{"model":"base_de_dados.indicepluviometrico","pk":38918,"fields":{"ano":"2013","mes":"03","media_pluviometrica":459.2,"cidade":240}},{"model":"base_de_dados.indicepluviometrico","pk":38919,"fields":{"ano":"2013","mes":"04","media_pluviometrica":366.6,"cidade":240}},{"model":"base_de_dados.indicepluviometrico","pk":38920,"fields":{"ano":"2013","mes":"05","media_pluviometrica":286.2,"cidade":240}},{"model":"base_de_dados.indicepluviometrico","pk":38921,"fields":{"ano":"2013","mes":"06","media_pluviometrica":104.8,"cidade":240}},{"model":"base_de_dados.indicepluviometrico","pk":38922,"fields":{"ano":"2013","mes":"07","media_pluviometrica":185.6,"cidade":240}},{"model":"base_de_dados.indicepluviometrico","pk":38923,"fields":{"ano":"2013","mes":"08","media_pluviometrica":154.8,"cidade":240}},{"model":"base_de_dados.indicepluviometrico","pk":38924,"fields":{"ano":"2013","mes":"09","media_pluviometrica":123.6,"cidade":240}},{"model":"base_de_dados.indicepluviometrico","pk":38925,"fields":{"ano":"2013","mes":"10","media_pluviometrica":97.2,"cidade":240}},{"model":"base_de_dados.indicepluviometrico","pk":38926,"fields":{"ano":"2013","mes":"11","media_pluviometrica":192.4,"cidade":240}},{"model":"base_de_dados.indicepluviometrico","pk":38927,"fields":{"ano":"2013","mes":"12","media_pluviometrica":282.4,"cidade":240}},{"model":"base_de_dados.indicepluviometrico","pk":38928,"fields":{"ano":"2014","mes":"01","media_pluviometrica":356.4,"cidade":240}},{"model":"base_de_dados.indicepluviometrico","pk":38929,"fields":{"ano":"2014","mes":"02","media_pluviometrica":480.6,"cidade":240}},{"model":"base_de_dados.indicepluviometrico","pk":38930,"fields":{"ano":"2014","mes":"03","media_pluviometrica":362.6,"cidade":240}},{"model":"base_de_dados.indicepluviometrico","pk":38931,"fields":{"ano":"2014","mes":"04","media_pluviometrica":533.4,"cidade":240}},{"model":"base_de_dados.indicepluviometrico","pk":38932,"fields":{"ano":"2014","mes":"05","media_pluviometrica":355.4,"cidade":240}},{"model":"base_de_dados.indicepluviometrico","pk":38933,"fields":{"ano":"2014","mes":"06","media_pluviometrica":253.2,"cidade":240}},{"model":"base_de_dados.indicepluviometrico","pk":38934,"fields":{"ano":"2014","mes":"07","media_pluviometrica":171.8,"cidade":240}},{"model":"base_de_dados.indicepluviometrico","pk":38935,"fields":{"ano":"2014","mes":"08","media_pluviometrica":82.0,"cidade":240}},{"model":"base_de_dados.indicepluviometrico","pk":38936,"fields":{"ano":"2014","mes":"09","media_pluviometrica":192.6,"cidade":240}},{"model":"base_de_dados.indicepluviometrico","pk":38937,"fields":{"ano":"2014","mes":"10","media_pluviometrica":99.4,"cidade":240}},{"model":"base_de_dados.indicepluviometrico","pk":38938,"fields":{"ano":"2014","mes":"11","media_pluviometrica":44.4,"cidade":240}},{"model":"base_de_dados.indicepluviometrico","pk":38939,"fields":{"ano":"2014","mes":"12","media_pluviometrica":129.6,"cidade":240}},{"model":"base_de_dados.indicepluviometrico","pk":38940,"fields":{"ano":"2015","mes":"01","media_pluviometrica":399.4,"cidade":240}},{"model":"base_de_dados.indicepluviometrico","pk":38941,"fields":{"ano":"2015","mes":"02","media_pluviometrica":273.8,"cidade":240}},{"model":"base_de_dados.indicepluviometrico","pk":38942,"fields":{"ano":"2015","mes":"03","media_pluviometrica":440.6,"cidade":240}},{"model":"base_de_dados.indicepluviometrico","pk":38943,"fields":{"ano":"2015","mes":"04","media_pluviometrica":493.0,"cidade":240}},{"model":"base_de_dados.indicepluviometrico","pk":38944,"fields":{"ano":"2015","mes":"05","media_pluviometrica":319.0,"cidade":240}},{"model":"base_de_dados.indicepluviometrico","pk":38945,"fields":{"ano":"2015","mes":"06","media_pluviometrica":151.6,"cidade":240}},{"model":"base_de_dados.indicepluviometrico","pk":38946,"fields":{"ano":"2015","mes":"07","media_pluviometrica":166.8,"cidade":240}},{"model":"base_de_dados.indicepluviometrico","pk":38947,"fields":{"ano":"2015","mes":"08","media_pluviometrica":94.2,"cidade":240}},{"model":"base_de_dados.indicepluviometrico","pk":38948,"fields":{"ano":"2015","mes":"09","media_pluviometrica":55.0,"cidade":240}},{"model":"base_de_dados.indicepluviometrico","pk":38949,"fields":{"ano":"2015","mes":"10","media_pluviometrica":73.4,"cidade":240}},{"model":"base_de_dados.indicepluviometrico","pk":38950,"fields":{"ano":"2015","mes":"11","media_pluviometrica":60.4,"cidade":240}},{"model":"base_de_dados.indicepluviometrico","pk":38951,"fields":{"ano":"2015","mes":"12","media_pluviometrica":228.8,"cidade":240}},{"model":"base_de_dados.indicepluviometrico","pk":38952,"fields":{"ano":"2016","mes":"01","media_pluviometrica":262.0,"cidade":240}},{"model":"base_de_dados.indicepluviometrico","pk":38953,"fields":{"ano":"2016","mes":"02","media_pluviometrica":518.4,"cidade":240}},{"model":"base_de_dados.indicepluviometrico","pk":38954,"fields":{"ano":"2016","mes":"03","media_pluviometrica":482.2,"cidade":240}},{"model":"base_de_dados.indicepluviometrico","pk":38955,"fields":{"ano":"2016","mes":"04","media_pluviometrica":300.0,"cidade":240}},{"model":"base_de_dados.indicepluviometrico","pk":38956,"fields":{"ano":"2016","mes":"05","media_pluviometrica":250.2,"cidade":240}},{"model":"base_de_dados.indicepluviometrico","pk":38957,"fields":{"ano":"2016","mes":"06","media_pluviometrica":207.0,"cidade":240}},{"model":"base_de_dados.indicepluviometrico","pk":38958,"fields":{"ano":"2016","mes":"07","media_pluviometrica":128.8,"cidade":240}},{"model":"base_de_dados.indicepluviometrico","pk":38959,"fields":{"ano":"2016","mes":"08","media_pluviometrica":122.4,"cidade":240}},{"model":"base_de_dados.indicepluviometrico","pk":38960,"fields":{"ano":"2016","mes":"09","media_pluviometrica":106.8,"cidade":240}},{"model":"base_de_dados.indicepluviometrico","pk":38961,"fields":{"ano":"2016","mes":"10","media_pluviometrica":79.4,"cidade":240}},{"model":"base_de_dados.indicepluviometrico","pk":38962,"fields":{"ano":"2016","mes":"11","media_pluviometrica":95.2,"cidade":240}},{"model":"base_de_dados.indicepluviometrico","pk":38963,"fields":{"ano":"2016","mes":"12","media_pluviometrica":263.4,"cidade":240}},{"model":"base_de_dados.indicepluviometrico","pk":38964,"fields":{"ano":"2017","mes":"01","media_pluviometrica":573.6,"cidade":240}},{"model":"base_de_dados.indicepluviometrico","pk":38965,"fields":{"ano":"2017","mes":"02","media_pluviometrica":417.2,"cidade":240}},{"model":"base_de_dados.indicepluviometrico","pk":38966,"fields":{"ano":"2017","mes":"03","media_pluviometrica":574.2,"cidade":240}},{"model":"base_de_dados.indicepluviometrico","pk":38967,"fields":{"ano":"2017","mes":"04","media_pluviometrica":417.2,"cidade":240}},{"model":"base_de_dados.indicepluviometrico","pk":38968,"fields":{"ano":"2017","mes":"05","media_pluviometrica":235.6,"cidade":240}},{"model":"base_de_dados.indicepluviometrico","pk":38969,"fields":{"ano":"2017","mes":"06","media_pluviometrica":151.4,"cidade":240}},{"model":"base_de_dados.indicepluviometrico","pk":38970,"fields":{"ano":"2017","mes":"07","media_pluviometrica":27.8,"cidade":240}},{"model":"base_de_dados.indicepluviometrico","pk":38971,"fields":{"ano":"2017","mes":"08","media_pluviometrica":214.8,"cidade":240}},{"model":"base_de_dados.indicepluviometrico","pk":38972,"fields":{"ano":"2017","mes":"09","media_pluviometrica":58.8,"cidade":240}},{"model":"base_de_dados.indicepluviometrico","pk":38973,"fields":{"ano":"2017","mes":"10","media_pluviometrica":236.6,"cidade":240}},{"model":"base_de_dados.indicepluviometrico","pk":38974,"fields":{"ano":"2017","mes":"11","media_pluviometrica":110.2,"cidade":240}},{"model":"base_de_dados.indicepluviometrico","pk":38975,"fields":{"ano":"2017","mes":"12","media_pluviometrica":257.6,"cidade":240}},{"model":"base_de_dados.indicepluviometrico","pk":38976,"fields":{"ano":"2018","mes":"01","media_pluviometrica":354.2,"cidade":240}},{"model":"base_de_dados.indicepluviometrico","pk":38977,"fields":{"ano":"2018","mes":"02","media_pluviometrica":651.8,"cidade":240}},{"model":"base_de_dados.indicepluviometrico","pk":38978,"fields":{"ano":"2018","mes":"03","media_pluviometrica":467.6,"cidade":240}},{"model":"base_de_dados.indicepluviometrico","pk":38979,"fields":{"ano":"2018","mes":"04","media_pluviometrica":495.8,"cidade":240}},{"model":"base_de_dados.indicepluviometrico","pk":38980,"fields":{"ano":"2018","mes":"05","media_pluviometrica":476.0,"cidade":240}},{"model":"base_de_dados.indicepluviometrico","pk":38981,"fields":{"ano":"2018","mes":"06","media_pluviometrica":107.4,"cidade":240}},{"model":"base_de_dados.indicepluviometrico","pk":38982,"fields":{"ano":"2018","mes":"07","media_pluviometrica":121.8,"cidade":240}},{"model":"base_de_dados.indicepluviometrico","pk":38983,"fields":{"ano":"2018","mes":"08","media_pluviometrica":222.4,"cidade":240}},{"model":"base_de_dados.indicepluviometrico","pk":38984,"fields":{"ano":"2018","mes":"09","media_pluviometrica":225.0,"cidade":240}},{"model":"base_de_dados.indicepluviometrico","pk":38985,"fields":{"ano":"2018","mes":"10","media_pluviometrica":268.0,"cidade":240}},{"model":"base_de_dados.indicepluviometrico","pk":38986,"fields":{"ano":"2018","mes":"11","media_pluviometrica":317.2,"cidade":240}},{"model":"base_de_dados.indicepluviometrico","pk":38987,"fields":{"ano":"2018","mes":"12","media_pluviometrica":465.6,"cidade":240}},{"model":"base_de_dados.indicepluviometrico","pk":38988,"fields":{"ano":"2019","mes":"01","media_pluviometrica":370.8,"cidade":240}},{"model":"base_de_dados.indicepluviometrico","pk":38989,"fields":{"ano":"2019","mes":"02","media_pluviometrica":426.6,"cidade":240}},{"model":"base_de_dados.indicepluviometrico","pk":38990,"fields":{"ano":"2019","mes":"03","media_pluviometrica":763.8,"cidade":240}},{"model":"base_de_dados.indicepluviometrico","pk":38991,"fields":{"ano":"2019","mes":"04","media_pluviometrica":559.6,"cidade":240}},{"model":"base_de_dados.indicepluviometrico","pk":38992,"fields":{"ano":"2019","mes":"05","media_pluviometrica":443.4,"cidade":240}},{"model":"base_de_dados.indicepluviometrico","pk":38993,"fields":{"ano":"2019","mes":"06","media_pluviometrica":253.6,"cidade":240}},{"model":"base_de_dados.indicepluviometrico","pk":38994,"fields":{"ano":"2019","mes":"07","media_pluviometrica":156.2,"cidade":240}},{"model":"base_de_dados.indicepluviometrico","pk":38995,"fields":{"ano":"2019","mes":"08","media_pluviometrica":151.0,"cidade":240}},{"model":"base_de_dados.indicepluviometrico","pk":38996,"fields":{"ano":"2019","mes":"09","media_pluviometrica":232.6,"cidade":240}},{"model":"base_de_dados.indicepluviometrico","pk":38997,"fields":{"ano":"2019","mes":"10","media_pluviometrica":275.0,"cidade":240}},{"model":"base_de_dados.indicepluviometrico","pk":38998,"fields":{"ano":"2019","mes":"11","media_pluviometrica":250.4,"cidade":240}},{"model":"base_de_dados.indicepluviometrico","pk":38999,"fields":{"ano":"2019","mes":"12","media_pluviometrica":385.0,"cidade":240}}]